{"assets/fonts/Poppins-Bold.ttf":["assets/fonts/Poppins-Bold.ttf"],"assets/fonts/Poppins-Light.ttf":["assets/fonts/Poppins-Light.ttf"],"assets/fonts/Poppins-Regular.ttf":["assets/fonts/Poppins-Regular.ttf"],"assets/icons/question.svg":["assets/icons/question.svg"],"assets/icons/telegram.svg":["assets/icons/telegram.svg"],"assets/images/app_icon.png":["assets/images/app_icon.png"],"assets/images/crv_logo.png":["assets/images/crv_logo.png"],"assets/images/global_banner.png":["assets/images/global_banner.png"],"assets/images/icon_appbar.png":["assets/images/icon_appbar.png"],"assets/images/infinite-reality.png":["assets/images/infinite-reality.png"]}